lightodm/__init__.py
lightodm/connection.py
lightodm/model.py
lightodm/py.typed
lightodm-0.1.0.dist-info/METADATA
lightodm-0.1.0.dist-info/WHEEL
lightodm-0.1.0.dist-info/licenses/LICENSE
lightodm-0.1.0.dist-info/RECORD
