Metadata-Version: 2.4
Name: lightodm
Version: 0.1.0
Summary: Lightweight MongoDB ODM - Simple async/sync Object-Document Mapper for MongoDB
Project-URL: Homepage, https://github.com/Aprova-GmbH/lightodm
Project-URL: Repository, https://github.com/Aprova-GmbH/lightodm
Project-URL: Documentation, https://github.com/Aprova-GmbH/lightodm#readme
Project-URL: Issues, https://github.com/Aprova-GmbH/lightodm/issues
Author-email: Andrey Vykhodtsev <vya@aprova.ch>
License: Apache-2.0
License-File: LICENSE
Keywords: async,database,mongodb,motor,odm,orm,pydantic,pymongo
Classifier: Development Status :: 4 - Beta
Classifier: Intended Audience :: Developers
Classifier: License :: OSI Approved :: Apache Software License
Classifier: Programming Language :: Python :: 3
Classifier: Programming Language :: Python :: 3.8
Classifier: Programming Language :: Python :: 3.9
Classifier: Programming Language :: Python :: 3.10
Classifier: Programming Language :: Python :: 3.11
Classifier: Programming Language :: Python :: 3.12
Classifier: Topic :: Database
Classifier: Topic :: Software Development :: Libraries :: Python Modules
Classifier: Typing :: Typed
Requires-Python: >=3.8
Requires-Dist: motor>=3.0
Requires-Dist: pydantic>=2.0
Requires-Dist: pymongo>=4.0
Provides-Extra: dev
Requires-Dist: black>=23.0; extra == 'dev'
Requires-Dist: mongomock>=4.0; extra == 'dev'
Requires-Dist: mypy>=1.0; extra == 'dev'
Requires-Dist: pytest-asyncio>=0.21; extra == 'dev'
Requires-Dist: pytest-cov>=4.0; extra == 'dev'
Requires-Dist: pytest>=7.0; extra == 'dev'
Requires-Dist: ruff>=0.1; extra == 'dev'
Requires-Dist: sphinx-rtd-theme>=2.0; extra == 'dev'
Requires-Dist: sphinx>=7.0; extra == 'dev'
